pinviz/__init__.py
pinviz/assets/gpio_pins.svg
pinviz/assets/logo_512.png
pinviz/assets/pi_4_mod.svg
pinviz/assets/pi_5_mod.svg
pinviz/assets/pico_mod.svg
pinviz/board_configs/raspberry_pi_4.json
pinviz/board_configs/raspberry_pi_5.json
pinviz/board_configs/raspberry_pi_pico.json
pinviz/board_renderer.py
pinviz/boards.py
pinviz/cli/__init__.py
pinviz/cli/commands/__init__.py
pinviz/cli/commands/device.py
pinviz/cli/commands/example.py
pinviz/cli/commands/list.py
pinviz/cli/commands/render.py
pinviz/cli/commands/validate.py
pinviz/cli/context.py
pinviz/cli/decorators.py
pinviz/cli/output.py
pinviz/cli/types.py
pinviz/cli/validation_output.py
pinviz/component_renderer.py
pinviz/config_loader.py
pinviz/connection_graph.py
pinviz/constants.py
pinviz/device_configs/displays/i2c_device.json
pinviz/device_configs/displays/spi_device.json
pinviz/device_configs/displays/ssd1306.json
pinviz/device_configs/io/button.json
pinviz/device_configs/io/mcp3008.json
pinviz/device_configs/leds/ir_led_ring.json
pinviz/device_configs/leds/led.json
pinviz/device_configs/sensors/bh1750.json
pinviz/device_configs/sensors/bme280.json
pinviz/device_configs/sensors/dht22.json
pinviz/device_configs/sensors/ds18b20.json
pinviz/device_configs/sensors/hcsr04.json
pinviz/device_configs/sensors/pir.json
pinviz/device_validator.py
pinviz/device_wizard.py
pinviz/devices/__init__.py
pinviz/devices/loader.py
pinviz/devices/registry.py
pinviz/layout.py
pinviz/logging_config.py
pinviz/mcp/README.md
pinviz/mcp/__init__.py
pinviz/mcp/connection_builder.py
pinviz/mcp/device_manager.py
pinviz/mcp/device_validator.py
pinviz/mcp/devices/database.json
pinviz/mcp/devices/schema.json
pinviz/mcp/devices/user_devices.json
pinviz/mcp/docs/CONTRIBUTING_DEVICES.md
pinviz/mcp/docs/INSTALLATION.md
pinviz/mcp/docs/USAGE.md
pinviz/mcp/parser.py
pinviz/mcp/pin_assignment.py
pinviz/mcp/server.py
pinviz/model.py
pinviz/py.typed
pinviz/render_constants.py
pinviz/render_svg.py
pinviz/schemas.py
pinviz/theme.py
pinviz/utils.py
pinviz-0.12.0.dist-info/WHEEL
pinviz-0.12.0.dist-info/entry_points.txt
pinviz-0.12.0.dist-info/METADATA
pinviz-0.12.0.dist-info/RECORD
