Metadata-Version: 2.3
Name: pinviz
Version: 0.12.0
Summary: Programmatically generate Raspberry Pi GPIO connection diagrams
Keywords: raspberry-pi,gpio,diagram,wiring,visualization,electronics,svg,raspberry-pi-5,hardware,circuit-diagram
Author: Even Nordstad
Author-email: Even Nordstad <even.nordstad@gmail.com>
License: MIT
Classifier: Development Status :: 4 - Beta
Classifier: Intended Audience :: Developers
Classifier: Intended Audience :: Education
Classifier: Intended Audience :: Science/Research
Classifier: Topic :: Software Development :: Libraries :: Python Modules
Classifier: Topic :: Scientific/Engineering :: Visualization
Classifier: Topic :: System :: Hardware
Classifier: License :: OSI Approved :: MIT License
Classifier: Programming Language :: Python :: 3
Classifier: Programming Language :: Python :: 3.12
Classifier: Programming Language :: Python :: 3.13
Classifier: Operating System :: OS Independent
Classifier: Typing :: Typed
Requires-Dist: drawsvg~=2.4
Requires-Dist: pyyaml>=6.0.1
Requires-Dist: typer>=0.12.0
Requires-Dist: rich>=13.7.0
Requires-Dist: pydantic>=2.0.0
Requires-Dist: pydantic-settings>=2.0.0
Requires-Dist: questionary>=2.0.0
Requires-Dist: platformdirs>=4.0.0
Requires-Dist: mcp>=1.22.0
Requires-Dist: httpx>=0.28.0
Requires-Dist: beautifulsoup4>=4.12.0
Requires-Dist: structlog>=24.1.0
Requires-Python: >=3.12
Project-URL: Homepage, https://nordstad.github.io/PinViz/
Project-URL: Repository, https://github.com/nordstad/PinViz
Project-URL: Documentation, https://nordstad.github.io/PinViz/
Project-URL: Bug Tracker, https://github.com/nordstad/PinViz/issues
Project-URL: Changelog, https://github.com/nordstad/PinViz/blob/main/CHANGELOG.md
